{
    "needsErrorInfo": false,
    "boxShadow": "none",
    "mobileBottomRow": 22,
    "widgetName": "Image2",
    "displayName": "Image",
    "iconSVG": "/static/media/icon.69b0f0dd810281fbd6e34fc2c3f39344.svg",
    "topRow": 9,
    "bottomRow": 49,
    "parentRowSpace": 10,
    "type": "IMAGE_WIDGET",
    "hideCard": false,
    "mobileRightColumn": 55,
    "animateLoading": true,
    "parentColumnSpace": 17.9375,
    "dynamicTriggerPathList": [],
    "imageShape": "RECTANGLE",
    "leftColumn": 44,
    "dynamicBindingPathList": [{"key": "borderRadius"}],
    "defaultImage": "https://cdn.hero.page/pfp/f6875ee2-8b65-4313-9731-01295d385b64-levi-ackerman-in-casual-look-cool-anime-male-pfp-1.png",
    "flexVerticalAlignment": "start",
    "key": "vzitw7spv7",
    "image": "",
    "isDeprecated": false,
    "rightColumn": 62,
    "objectFit": "cover",
    "widgetId": "tukdda5cqz",
    "isVisible": true,
    "version": 1,
    "parentId": "0",
    "tags": ["Media"],
    "renderMode": "CANVAS",
    "isLoading": false,
    "mobileTopRow": 10,
    "maxZoomLevel": 1,
    "enableDownload": false,
    "borderRadius": "{{appsmith.theme.borderRadius.appBorderRadius}}",
    "mobileLeftColumn": 43,
    "enableRotation": false
}